botoplus/__init__.py
botoplus/deflation.py
botoplus/identity.py
botoplus/organization.py
botoplus-2025.5.5.dist-info/licenses/LICENSE
botoplus-2025.5.5.dist-info/METADATA
botoplus-2025.5.5.dist-info/WHEEL
botoplus-2025.5.5.dist-info/top_level.txt
botoplus-2025.5.5.dist-info/RECORD
