Metadata-Version: 2.4
Name: botoplus
Version: 2025.5.5
Summary: Python Library for Jupyter Notebooks that provides Security Operations the Threat Detection and Response capabilities needed during an Amazon Web Services (AWS) investigation.
Home-page: https://github.com/jblukach/botoplus
Author: John Lukach
Author-email: hello@4n6ir.com
License: Apache-2.0
Requires-Python: >=3.9
License-File: LICENSE
Requires-Dist: aws-sso-lib
Requires-Dist: boto3
Requires-Dist: typer
Dynamic: author
Dynamic: author-email
Dynamic: description
Dynamic: description-content-type
Dynamic: home-page
Dynamic: license
Dynamic: license-file
Dynamic: requires-dist
Dynamic: requires-python
Dynamic: summary
